Metadata-Version: 2.1
Name: ngs-destruct
Version: 0.4.21
Summary: Destruct is a tool for joint prediction of rearrangement breakpoints from single or multiple tumour samples
Home-page: http://bitbucket.org/dranew/destruct
Download-URL: https://bitbucket.org/dranew/destruct/get/v0.4.21.tar.gz
Author: Andrew McPherson
Author-email: andrew.mcpherson@gmail.com
License: UNKNOWN
Keywords: scientific,sequence analysis,cancer
Platform: UNKNOWN
